Metadata-Version: 1.0
Name: taskyy
Version: 0.1.1
Summary: Taskyy is a command-line app for you remainders for mac.
Home-page: https://github.com/MohammedAkhil
Author: Mohammed Akhil
Author-email: akhilmohammed05@gmail.com
License: UNKNOWN
Platform: UNKNOWN
